{
  "0009-7.mp4": {
    "keep": false,
    "gap_start": null,
    "gap_end": null,
    "reason": "QUALITY_LOW"
  },
  "0010-7.mp4": {
    "keep": false,
    "gap_start": null,
    "gap_end": null,
    "reason": "After 3 tries: Mean magnitude 0.431 <= 1.0"
  },
  "0011-7.mp4": {
    "keep": false,
    "gap_start": null,
    "gap_end": null,
    "reason": "QUALITY_LOW"
  },
  "0013-7.mp4": {
    "keep": false,
    "gap_start": null,
    "gap_end": null,
    "reason": "After 3 tries: Mean magnitude 0.229 <= 1.0"
  },
  "0015-7.mp4": {
    "keep": false,
    "gap_start": null,
    "gap_end": null,
    "reason": "After 3 tries: Mean magnitude 0.365 <= 1.0"
  },
  "0018-7.mp4": {
    "keep": true,
    "gap_start": 7.3,
    "gap_end": 12.92,
    "reason": null
  },
  "0019-7.mp4": {
    "keep": false,
    "gap_start": null,
    "gap_end": null,
    "reason": "QUALITY_LOW"
  },
  "0022-7.mp4": {
    "keep": false,
    "gap_start": null,
    "gap_end": null,
    "reason": "After 3 tries: Mean magnitude 0.867 <= 1.0"
  },
  "0024-7.mp4": {
    "keep": false,
    "gap_start": null,
    "gap_end": null,
    "reason": "QUALITY_LOW"
  },
  "0026-7.mp4": {
    "keep": true,
    "gap_start": 6.88,
    "gap_end": 13.41,
    "reason": null
  },
  "0030-7.mp4": {
    "keep": false,
    "gap_start": null,
    "gap_end": null,
    "reason": "QUALITY_LOW"
  },
  "0032-7.mp4": {
    "keep": true,
    "gap_start": 15.55,
    "gap_end": 29.26,
    "reason": null
  },
  "0033-7.mp4": {
    "keep": false,
    "gap_start": null,
    "gap_end": null,
    "reason": "After 3 tries: Mean magnitude 0.051 <= 1.0"
  },
  "0034-7.mp4": {
    "keep": false,
    "gap_start": null,
    "gap_end": null,
    "reason": "After 3 tries: Mean magnitude 0.590 <= 1.0"
  },
  "0040-7.mp4": {
    "keep": false,
    "gap_start": null,
    "gap_end": null,
    "reason": "After 3 tries: Mean magnitude 0.473 <= 1.0"
  },
  "0041-7.mp4": {
    "keep": false,
    "gap_start": null,
    "gap_end": null,
    "reason": "QUALITY_LOW"
  },
  "0045-7.mp4": {
    "keep": false,
    "gap_start": null,
    "gap_end": null,
    "reason": "QUALITY_LOW"
  },
  "0052-7.mp4": {
    "keep": true,
    "gap_start": 18.45,
    "gap_end": 38.05,
    "reason": null
  },
  "0053-7.mp4": {
    "keep": false,
    "gap_start": null,
    "gap_end": null,
    "reason": "QUALITY_LOW"
  },
  "0055-7.mp4": {
    "keep": true,
    "gap_start": 6.67,
    "gap_end": 13.37,
    "reason": null
  },
  "0056-7.mp4": {
    "keep": false,
    "gap_start": null,
    "gap_end": null,
    "reason": "After 3 tries: Mean magnitude 0.464 <= 1.0"
  },
  "0057-7.mp4": {
    "keep": false,
    "gap_start": null,
    "gap_end": null,
    "reason": "QUALITY_LOW"
  },
  "0058-7.mp4": {
    "keep": false,
    "gap_start": null,
    "gap_end": null,
    "reason": "QUALITY_LOW"
  },
  "0061-7.mp4": {
    "keep": false,
    "gap_start": null,
    "gap_end": null,
    "reason": "After 3 tries: Mean magnitude 0.248 <= 1.0"
  },
  "0063-7.mp4": {
    "keep": false,
    "gap_start": null,
    "gap_end": null,
    "reason": "QUALITY_LOW"
  },
  "0065-7.mp4": {
    "keep": false,
    "gap_start": null,
    "gap_end": null,
    "reason": "QUALITY_LOW"
  },
  "0068-7.mp4": {
    "keep": true,
    "gap_start": 17.25,
    "gap_end": 34.8,
    "reason": null
  },
  "0071-7.mp4": {
    "keep": false,
    "gap_start": null,
    "gap_end": null,
    "reason": "QUALITY_LOW"
  },
  "0076-7.mp4": {
    "keep": false,
    "gap_start": null,
    "gap_end": null,
    "reason": "After 3 tries: Mean magnitude 0.334 <= 1.0"
  },
  "0078-7.mp4": {
    "keep": false,
    "gap_start": null,
    "gap_end": null,
    "reason": "After 3 tries: Mean magnitude 0.218 <= 1.0"
  },
  "0085-7.mp4": {
    "keep": false,
    "gap_start": null,
    "gap_end": null,
    "reason": "QUALITY_LOW"
  },
  "0086-7.mp4": {
    "keep": true,
    "gap_start": 11.25,
    "gap_end": 24.76,
    "reason": null
  },
  "0094-7.mp4": {
    "keep": true,
    "gap_start": 13.82,
    "gap_end": 22.32,
    "reason": null
  },
  "0097-7.mp4": {
    "keep": false,
    "gap_start": null,
    "gap_end": null,
    "reason": "QUALITY_LOW"
  },
  "0103-7.mp4": {
    "keep": false,
    "gap_start": null,
    "gap_end": null,
    "reason": "QUALITY_LOW"
  },
  "0106-7.mp4": {
    "keep": true,
    "gap_start": 17.69,
    "gap_end": 38.79,
    "reason": null
  },
  "0114-7.mp4": {
    "keep": false,
    "gap_start": null,
    "gap_end": null,
    "reason": "After 3 tries: Mean magnitude 0.270 <= 1.0"
  },
  "0121-7.mp4": {
    "keep": false,
    "gap_start": null,
    "gap_end": null,
    "reason": "QUALITY_LOW"
  },
  "0136-7.mp4": {
    "keep": false,
    "gap_start": null,
    "gap_end": null,
    "reason": "After 3 tries: Mean magnitude 0.265 <= 1.0"
  },
  "0141-7.mp4": {
    "keep": false,
    "gap_start": null,
    "gap_end": null,
    "reason": "QUALITY_LOW"
  },
  "0143-7.mp4": {
    "keep": false,
    "gap_start": null,
    "gap_end": null,
    "reason": "After 3 tries: Mean magnitude 0.528 <= 1.0"
  },
  "0144-7.mp4": {
    "keep": false,
    "gap_start": null,
    "gap_end": null,
    "reason": "QUALITY_LOW"
  },
  "0148-7.mp4": {
    "keep": false,
    "gap_start": null,
    "gap_end": null,
    "reason": "After 3 tries: Mean magnitude 0.635 <= 1.0"
  },
  "0150-7.mp4": {
    "keep": false,
    "gap_start": null,
    "gap_end": null,
    "reason": "After 3 tries: Mean magnitude 0.406 <= 1.0"
  },
  "0153-7.mp4": {
    "keep": false,
    "gap_start": null,
    "gap_end": null,
    "reason": "After 3 tries: Mean magnitude 0.707 <= 1.0"
  },
  "0158-7.mp4": {
    "keep": false,
    "gap_start": null,
    "gap_end": null,
    "reason": "QUALITY_LOW"
  },
  "0163-7.mp4": {
    "keep": true,
    "gap_start": 4.22,
    "gap_end": 8.9,
    "reason": null
  },
  "0164-7.mp4": {
    "keep": true,
    "gap_start": 11.1,
    "gap_end": 17.26,
    "reason": null
  },
  "0166-7.mp4": {
    "keep": true,
    "gap_start": 11.15,
    "gap_end": 22.12,
    "reason": null
  },
  "0168-7.mp4": {
    "keep": true,
    "gap_start": 15.47,
    "gap_end": 28.63,
    "reason": null
  },
  "0170-7.mp4": {
    "keep": false,
    "gap_start": null,
    "gap_end": null,
    "reason": "QUALITY_LOW"
  },
  "0172-7.mp4": {
    "keep": true,
    "gap_start": 11.99,
    "gap_end": 19.92,
    "reason": null
  },
  "0173-7.mp4": {
    "keep": false,
    "gap_start": null,
    "gap_end": null,
    "reason": "After 3 tries: Mean magnitude 0.277 <= 1.0"
  },
  "0175-7.mp4": {
    "keep": false,
    "gap_start": null,
    "gap_end": null,
    "reason": "QUALITY_LOW"
  },
  "0176-7.mp4": {
    "keep": true,
    "gap_start": 15.62,
    "gap_end": 33.34,
    "reason": null
  },
  "0177-7.mp4": {
    "keep": false,
    "gap_start": null,
    "gap_end": null,
    "reason": "QUALITY_LOW"
  },
  "0178-7.mp4": {
    "keep": false,
    "gap_start": null,
    "gap_end": null,
    "reason": "After 3 tries: Mean magnitude 0.081 <= 1.0"
  },
  "0180-7.mp4": {
    "keep": false,
    "gap_start": null,
    "gap_end": null,
    "reason": "QUALITY_LOW"
  },
  "0184-7.mp4": {
    "keep": true,
    "gap_start": 6.19,
    "gap_end": 10.78,
    "reason": null
  },
  "0186-7.mp4": {
    "keep": false,
    "gap_start": null,
    "gap_end": null,
    "reason": "QUALITY_LOW"
  },
  "0188-7.mp4": {
    "keep": false,
    "gap_start": null,
    "gap_end": null,
    "reason": "QUALITY_LOW"
  },
  "0191-7.mp4": {
    "keep": false,
    "gap_start": null,
    "gap_end": null,
    "reason": "After 3 tries: Mean magnitude 0.193 <= 1.0"
  },
  "0192-7.mp4": {
    "keep": false,
    "gap_start": null,
    "gap_end": null,
    "reason": "QUALITY_LOW"
  },
  "0193-7.mp4": {
    "keep": false,
    "gap_start": null,
    "gap_end": null,
    "reason": "After 3 tries: Mean magnitude 0.801 <= 1.0"
  },
  "0203-7.mp4": {
    "keep": false,
    "gap_start": null,
    "gap_end": null,
    "reason": "QUALITY_LOW"
  },
  "0204-7.mp4": {
    "keep": false,
    "gap_start": null,
    "gap_end": null,
    "reason": "After 3 tries: Mean magnitude 0.812 <= 1.0"
  },
  "0205-7.mp4": {
    "keep": false,
    "gap_start": null,
    "gap_end": null,
    "reason": "After 3 tries: Mean magnitude 0.270 <= 1.0"
  },
  "0208-7.mp4": {
    "keep": true,
    "gap_start": 18.65,
    "gap_end": 34.18,
    "reason": null
  },
  "0211-7.mp4": {
    "keep": false,
    "gap_start": null,
    "gap_end": null,
    "reason": "QUALITY_LOW"
  },
  "0212-7.mp4": {
    "keep": false,
    "gap_start": null,
    "gap_end": null,
    "reason": "After 3 tries: Mean magnitude 0.631 <= 1.0"
  },
  "0215-7.mp4": {
    "keep": false,
    "gap_start": null,
    "gap_end": null,
    "reason": "After 3 tries: Mean magnitude 0.627 <= 1.0"
  },
  "0216-7.mp4": {
    "keep": false,
    "gap_start": null,
    "gap_end": null,
    "reason": "QUALITY_LOW"
  },
  "0220-7.mp4": {
    "keep": false,
    "gap_start": null,
    "gap_end": null,
    "reason": "After 3 tries: Mean magnitude 0.351 <= 1.0"
  },
  "0221-7.mp4": {
    "keep": false,
    "gap_start": null,
    "gap_end": null,
    "reason": "QUALITY_LOW"
  },
  "0223-7.mp4": {
    "keep": false,
    "gap_start": null,
    "gap_end": null,
    "reason": "QUALITY_LOW"
  },
  "0224-7.mp4": {
    "keep": false,
    "gap_start": null,
    "gap_end": null,
    "reason": "After 3 tries: Mean magnitude 0.804 <= 1.0"
  },
  "0225-7.mp4": {
    "keep": false,
    "gap_start": null,
    "gap_end": null,
    "reason": "After 3 tries: Mean magnitude 0.468 <= 1.0"
  },
  "0231-7.mp4": {
    "keep": false,
    "gap_start": null,
    "gap_end": null,
    "reason": "QUALITY_LOW"
  },
  "0232-7.mp4": {
    "keep": false,
    "gap_start": null,
    "gap_end": null,
    "reason": "QUALITY_LOW"
  },
  "0233-7.mp4": {
    "keep": true,
    "gap_start": 10.08,
    "gap_end": 17.49,
    "reason": null
  },
  "0234-7.mp4": {
    "keep": false,
    "gap_start": null,
    "gap_end": null,
    "reason": "After 3 tries: Mean magnitude 0.759 <= 1.0"
  },
  "0235-7.mp4": {
    "keep": true,
    "gap_start": 5.72,
    "gap_end": 10.0,
    "reason": null
  },
  "0237-7.mp4": {
    "keep": false,
    "gap_start": null,
    "gap_end": null,
    "reason": "After 3 tries: Mean magnitude 0.468 <= 1.0"
  },
  "0238-7.mp4": {
    "keep": false,
    "gap_start": null,
    "gap_end": null,
    "reason": "QUALITY_LOW"
  },
  "0239-7.mp4": {
    "keep": true,
    "gap_start": 9.6,
    "gap_end": 17.91,
    "reason": null
  },
  "0244-7.mp4": {
    "keep": true,
    "gap_start": 13.23,
    "gap_end": 28.5,
    "reason": null
  },
  "0247-7.mp4": {
    "keep": false,
    "gap_start": null,
    "gap_end": null,
    "reason": "QUALITY_LOW"
  },
  "0249-7.mp4": {
    "keep": false,
    "gap_start": null,
    "gap_end": null,
    "reason": "QUALITY_LOW"
  },
  "0250-7.mp4": {
    "keep": false,
    "gap_start": null,
    "gap_end": null,
    "reason": "After 3 tries: Mean magnitude 0.400 <= 1.0"
  },
  "0252-7.mp4": {
    "keep": true,
    "gap_start": 8.23,
    "gap_end": 16.99,
    "reason": null
  },
  "0253-7.mp4": {
    "keep": false,
    "gap_start": null,
    "gap_end": null,
    "reason": "QUALITY_LOW"
  },
  "0254-7.mp4": {
    "keep": true,
    "gap_start": 3.98,
    "gap_end": 7.81,
    "reason": null
  },
  "0257-7.mp4": {
    "keep": false,
    "gap_start": null,
    "gap_end": null,
    "reason": "QUALITY_LOW"
  },
  "0263-7.mp4": {
    "keep": true,
    "gap_start": 3.31,
    "gap_end": 7.6,
    "reason": null
  },
  "0264-7.mp4": {
    "keep": true,
    "gap_start": 7.52,
    "gap_end": 14.44,
    "reason": null
  },
  "0269-7.mp4": {
    "keep": false,
    "gap_start": null,
    "gap_end": null,
    "reason": "QUALITY_LOW"
  },
  "0270-7.mp4": {
    "keep": false,
    "gap_start": null,
    "gap_end": null,
    "reason": "QUALITY_LOW"
  },
  "0271-7.mp4": {
    "keep": true,
    "gap_start": 5.5,
    "gap_end": 10.73,
    "reason": null
  },
  "0272-7.mp4": {
    "keep": false,
    "gap_start": null,
    "gap_end": null,
    "reason": "After 3 tries: Mean magnitude 0.182 <= 1.0"
  },
  "0275-7.mp4": {
    "keep": false,
    "gap_start": null,
    "gap_end": null,
    "reason": "QUALITY_LOW"
  },
  "0277-7.mp4": {
    "keep": true,
    "gap_start": 9.69,
    "gap_end": 20.41,
    "reason": null
  },
  "0279-7.mp4": {
    "keep": false,
    "gap_start": null,
    "gap_end": null,
    "reason": "After 3 tries: Mean magnitude 0.039 <= 1.0"
  },
  "0284-7.mp4": {
    "keep": true,
    "gap_start": 3.61,
    "gap_end": 7.56,
    "reason": null
  },
  "0286-7.mp4": {
    "keep": true,
    "gap_start": 7.56,
    "gap_end": 15.13,
    "reason": null
  },
  "0290-7.mp4": {
    "keep": false,
    "gap_start": null,
    "gap_end": null,
    "reason": "QUALITY_LOW"
  },
  "0294-7.mp4": {
    "keep": true,
    "gap_start": 6.46,
    "gap_end": 9.92,
    "reason": null
  },
  "0299-7.mp4": {
    "keep": false,
    "gap_start": null,
    "gap_end": null,
    "reason": "QUALITY_LOW"
  },
  "0300-7.mp4": {
    "keep": false,
    "gap_start": null,
    "gap_end": null,
    "reason": "After 3 tries: Mean magnitude 0.581 <= 1.0"
  },
  "0302-7.mp4": {
    "keep": false,
    "gap_start": null,
    "gap_end": null,
    "reason": "QUALITY_LOW"
  },
  "0306-7.mp4": {
    "keep": false,
    "gap_start": null,
    "gap_end": null,
    "reason": "After 3 tries: Mean magnitude 0.556 <= 1.0"
  },
  "0309-7.mp4": {
    "keep": true,
    "gap_start": 14.42,
    "gap_end": 30.89,
    "reason": null
  },
  "0311-7.mp4": {
    "keep": false,
    "gap_start": null,
    "gap_end": null,
    "reason": "After 3 tries: Mean magnitude 0.702 <= 1.0"
  },
  "0317-7.mp4": {
    "keep": false,
    "gap_start": null,
    "gap_end": null,
    "reason": "QUALITY_LOW"
  },
  "0324-7.mp4": {
    "keep": false,
    "gap_start": null,
    "gap_end": null,
    "reason": "After 3 tries: Mean magnitude 0.317 <= 1.0"
  },
  "0329-7.mp4": {
    "keep": true,
    "gap_start": 10.91,
    "gap_end": 19.05,
    "reason": null
  },
  "0331-7.mp4": {
    "keep": false,
    "gap_start": null,
    "gap_end": null,
    "reason": "After 3 tries: Mean magnitude 0.502 <= 1.0"
  },
  "0333-7.mp4": {
    "keep": false,
    "gap_start": null,
    "gap_end": null,
    "reason": "QUALITY_LOW"
  },
  "0335-7.mp4": {
    "keep": false,
    "gap_start": null,
    "gap_end": null,
    "reason": "QUALITY_LOW"
  },
  "0337-7.mp4": {
    "keep": true,
    "gap_start": 26.85,
    "gap_end": 39.66,
    "reason": null
  },
  "0338-7.mp4": {
    "keep": false,
    "gap_start": null,
    "gap_end": null,
    "reason": "After 3 tries: Mean magnitude 0.595 <= 1.0"
  },
  "0343-7.mp4": {
    "keep": true,
    "gap_start": 5.42,
    "gap_end": 9.34,
    "reason": null
  },
  "0348-7.mp4": {
    "keep": false,
    "gap_start": null,
    "gap_end": null,
    "reason": "QUALITY_LOW"
  },
  "0349-7.mp4": {
    "keep": true,
    "gap_start": 9.51,
    "gap_end": 16.51,
    "reason": null
  },
  "0350-7.mp4": {
    "keep": false,
    "gap_start": null,
    "gap_end": null,
    "reason": "QUALITY_LOW"
  },
  "0352-7.mp4": {
    "keep": false,
    "gap_start": null,
    "gap_end": null,
    "reason": "After 3 tries: Mean magnitude 0.239 <= 1.0"
  },
  "0355-7.mp4": {
    "keep": false,
    "gap_start": null,
    "gap_end": null,
    "reason": "After 3 tries: Mean magnitude 0.383 <= 1.0"
  },
  "0359-7.mp4": {
    "keep": true,
    "gap_start": 25.09,
    "gap_end": 43.43,
    "reason": null
  },
  "0364-7.mp4": {
    "keep": false,
    "gap_start": null,
    "gap_end": null,
    "reason": "QUALITY_LOW"
  },
  "0366-7.mp4": {
    "keep": false,
    "gap_start": null,
    "gap_end": null,
    "reason": "After 3 tries: Mean magnitude 0.594 <= 1.0"
  },
  "0375-7.mp4": {
    "keep": false,
    "gap_start": null,
    "gap_end": null,
    "reason": "After 3 tries: Mean magnitude 0.612 <= 1.0"
  },
  "0376-7.mp4": {
    "keep": true,
    "gap_start": 10.84,
    "gap_end": 23.57,
    "reason": null
  },
  "0380-7.mp4": {
    "keep": true,
    "gap_start": 7.21,
    "gap_end": 15.87,
    "reason": null
  },
  "0382-7.mp4": {
    "keep": false,
    "gap_start": null,
    "gap_end": null,
    "reason": "QUALITY_LOW"
  },
  "0383-7.mp4": {
    "keep": false,
    "gap_start": null,
    "gap_end": null,
    "reason": "After 3 tries: Mean magnitude 0.908 <= 1.0"
  },
  "0385-7.mp4": {
    "keep": true,
    "gap_start": 16.91,
    "gap_end": 29.96,
    "reason": null
  },
  "0388-7.mp4": {
    "keep": true,
    "gap_start": 5.26,
    "gap_end": 10.44,
    "reason": null
  },
  "0389-7.mp4": {
    "keep": true,
    "gap_start": 9.76,
    "gap_end": 17.53,
    "reason": null
  },
  "0390-7.mp4": {
    "keep": true,
    "gap_start": 10.08,
    "gap_end": 23.75,
    "reason": null
  },
  "0391-7.mp4": {
    "keep": false,
    "gap_start": null,
    "gap_end": null,
    "reason": "QUALITY_LOW"
  },
  "0392-7.mp4": {
    "keep": false,
    "gap_start": null,
    "gap_end": null,
    "reason": "After 3 tries: Mean magnitude 0.797 <= 1.0"
  },
  "0393-7.mp4": {
    "keep": true,
    "gap_start": 27.9,
    "gap_end": 42.75,
    "reason": null
  },
  "0394-7.mp4": {
    "keep": false,
    "gap_start": null,
    "gap_end": null,
    "reason": "QUALITY_LOW"
  },
  "0395-7.mp4": {
    "keep": false,
    "gap_start": null,
    "gap_end": null,
    "reason": "After 3 tries: Mean magnitude 0.023 <= 1.0"
  },
  "0398-7.mp4": {
    "keep": false,
    "gap_start": null,
    "gap_end": null,
    "reason": "QUALITY_LOW"
  },
  "0401-7.mp4": {
    "keep": false,
    "gap_start": null,
    "gap_end": null,
    "reason": "After 3 tries: Mean magnitude 0.356 <= 1.0"
  },
  "0402-7.mp4": {
    "keep": false,
    "gap_start": null,
    "gap_end": null,
    "reason": "QUALITY_LOW"
  },
  "0408-7.mp4": {
    "keep": false,
    "gap_start": null,
    "gap_end": null,
    "reason": "QUALITY_LOW"
  },
  "0409-7.mp4": {
    "keep": false,
    "gap_start": null,
    "gap_end": null,
    "reason": "QUALITY_LOW"
  },
  "0413-7.mp4": {
    "keep": false,
    "gap_start": null,
    "gap_end": null,
    "reason": "After 3 tries: Mean magnitude 0.362 <= 1.0"
  },
  "0418-7.mp4": {
    "keep": false,
    "gap_start": null,
    "gap_end": null,
    "reason": "After 3 tries: Mean magnitude 0.382 <= 1.0"
  },
  "0424-7.mp4": {
    "keep": false,
    "gap_start": null,
    "gap_end": null,
    "reason": "After 3 tries: Mean magnitude 0.476 <= 1.0"
  },
  "0425-7.mp4": {
    "keep": true,
    "gap_start": 3.49,
    "gap_end": 6.55,
    "reason": null
  },
  "0428-7.mp4": {
    "keep": false,
    "gap_start": null,
    "gap_end": null,
    "reason": "QUALITY_LOW"
  },
  "0429-7.mp4": {
    "keep": false,
    "gap_start": null,
    "gap_end": null,
    "reason": "QUALITY_LOW"
  },
  "0437-7.mp4": {
    "keep": false,
    "gap_start": null,
    "gap_end": null,
    "reason": "QUALITY_LOW"
  },
  "0440-7.mp4": {
    "keep": true,
    "gap_start": 7.07,
    "gap_end": 15.83,
    "reason": null
  },
  "0442-7.mp4": {
    "keep": true,
    "gap_start": 17.85,
    "gap_end": 37.41,
    "reason": null
  },
  "0443-7.mp4": {
    "keep": true,
    "gap_start": 8.19,
    "gap_end": 18.98,
    "reason": null
  },
  "0444-7.mp4": {
    "keep": false,
    "gap_start": null,
    "gap_end": null,
    "reason": "After 3 tries: Mean magnitude 0.168 <= 1.0"
  },
  "0455-7.mp4": {
    "keep": false,
    "gap_start": null,
    "gap_end": null,
    "reason": "After 3 tries: Mean magnitude 0.339 <= 1.0"
  },
  "0457-7.mp4": {
    "keep": false,
    "gap_start": null,
    "gap_end": null,
    "reason": "After 3 tries: Mean magnitude 0.621 <= 1.0"
  },
  "0458-7.mp4": {
    "keep": false,
    "gap_start": null,
    "gap_end": null,
    "reason": "QUALITY_LOW"
  },
  "0460-7.mp4": {
    "keep": false,
    "gap_start": null,
    "gap_end": null,
    "reason": "After 3 tries: Mean magnitude 0.436 <= 1.0"
  },
  "0461-7.mp4": {
    "keep": false,
    "gap_start": null,
    "gap_end": null,
    "reason": "After 3 tries: Mean magnitude 0.626 <= 1.0"
  },
  "0462-7.mp4": {
    "keep": true,
    "gap_start": 6.41,
    "gap_end": 11.11,
    "reason": null
  },
  "0464-7.mp4": {
    "keep": true,
    "gap_start": 7.98,
    "gap_end": 17.27,
    "reason": null
  },
  "0469-7.mp4": {
    "keep": true,
    "gap_start": 21.27,
    "gap_end": 43.93,
    "reason": null
  },
  "0472-7.mp4": {
    "keep": false,
    "gap_start": null,
    "gap_end": null,
    "reason": "QUALITY_LOW"
  },
  "0476-7.mp4": {
    "keep": false,
    "gap_start": null,
    "gap_end": null,
    "reason": "After 3 tries: Mean magnitude 0.782 <= 1.0"
  },
  "0478-7.mp4": {
    "keep": false,
    "gap_start": null,
    "gap_end": null,
    "reason": "QUALITY_LOW"
  },
  "0479-7.mp4": {
    "keep": false,
    "gap_start": null,
    "gap_end": null,
    "reason": "QUALITY_LOW"
  },
  "0480-7.mp4": {
    "keep": false,
    "gap_start": null,
    "gap_end": null,
    "reason": "QUALITY_LOW"
  },
  "0481-7.mp4": {
    "keep": false,
    "gap_start": null,
    "gap_end": null,
    "reason": "QUALITY_LOW"
  },
  "0482-7.mp4": {
    "keep": false,
    "gap_start": null,
    "gap_end": null,
    "reason": "QUALITY_LOW"
  },
  "0483-7.mp4": {
    "keep": false,
    "gap_start": null,
    "gap_end": null,
    "reason": "After 3 tries: Mean magnitude 0.517 <= 1.0"
  },
  "0484-7.mp4": {
    "keep": true,
    "gap_start": 21.28,
    "gap_end": 40.46,
    "reason": null
  },
  "0487-7.mp4": {
    "keep": true,
    "gap_start": 10.53,
    "gap_end": 19.35,
    "reason": null
  },
  "0488-7.mp4": {
    "keep": false,
    "gap_start": null,
    "gap_end": null,
    "reason": "QUALITY_LOW"
  },
  "0489-7.mp4": {
    "keep": false,
    "gap_start": null,
    "gap_end": null,
    "reason": "After 3 tries: Mean magnitude 0.817 <= 1.0"
  },
  "0490-7.mp4": {
    "keep": true,
    "gap_start": 4.94,
    "gap_end": 12.45,
    "reason": null
  },
  "0492-7.mp4": {
    "keep": false,
    "gap_start": null,
    "gap_end": null,
    "reason": "After 3 tries: Mean magnitude 0.505 <= 1.0"
  },
  "0493-7.mp4": {
    "keep": true,
    "gap_start": 20.09,
    "gap_end": 42.86,
    "reason": null
  },
  "0498-7.mp4": {
    "keep": false,
    "gap_start": null,
    "gap_end": null,
    "reason": "QUALITY_LOW"
  },
  "0503-7.mp4": {
    "keep": true,
    "gap_start": 8.41,
    "gap_end": 17.42,
    "reason": null
  },
  "0505-7.mp4": {
    "keep": false,
    "gap_start": null,
    "gap_end": null,
    "reason": "QUALITY_LOW"
  },
  "0506-7.mp4": {
    "keep": true,
    "gap_start": 13.17,
    "gap_end": 30.86,
    "reason": null
  },
  "0514-7.mp4": {
    "keep": false,
    "gap_start": null,
    "gap_end": null,
    "reason": "After 3 tries: Mean magnitude 0.363 <= 1.0"
  },
  "0517-7.mp4": {
    "keep": false,
    "gap_start": null,
    "gap_end": null,
    "reason": "After 3 tries: Mean magnitude 0.199 <= 1.0"
  },
  "0519-7.mp4": {
    "keep": false,
    "gap_start": null,
    "gap_end": null,
    "reason": "After 3 tries: Mean magnitude 0.826 <= 1.0"
  },
  "0521-7.mp4": {
    "keep": true,
    "gap_start": 8.94,
    "gap_end": 17.88,
    "reason": null
  },
  "0523-7.mp4": {
    "keep": false,
    "gap_start": null,
    "gap_end": null,
    "reason": "QUALITY_LOW"
  },
  "0527-7.mp4": {
    "keep": true,
    "gap_start": 26.02,
    "gap_end": 48.1,
    "reason": null
  },
  "0532-7.mp4": {
    "keep": true,
    "gap_start": 20.48,
    "gap_end": 41.59,
    "reason": null
  },
  "0533-7.mp4": {
    "keep": false,
    "gap_start": null,
    "gap_end": null,
    "reason": "QUALITY_LOW"
  },
  "0538-7.mp4": {
    "keep": true,
    "gap_start": 13.12,
    "gap_end": 24.38,
    "reason": null
  },
  "0545-7.mp4": {
    "keep": false,
    "gap_start": null,
    "gap_end": null,
    "reason": "QUALITY_LOW"
  },
  "0555-7.mp4": {
    "keep": true,
    "gap_start": 7.06,
    "gap_end": 12.34,
    "reason": null
  },
  "0557-7.mp4": {
    "keep": true,
    "gap_start": 6.87,
    "gap_end": 11.66,
    "reason": null
  },
  "0560-7.mp4": {
    "keep": false,
    "gap_start": null,
    "gap_end": null,
    "reason": "QUALITY_LOW"
  },
  "0563-7.mp4": {
    "keep": true,
    "gap_start": 17.92,
    "gap_end": 39.92,
    "reason": null
  },
  "0564-7.mp4": {
    "keep": false,
    "gap_start": null,
    "gap_end": null,
    "reason": "After 3 tries: Mean magnitude 0.391 <= 1.0"
  },
  "0569-7.mp4": {
    "keep": false,
    "gap_start": null,
    "gap_end": null,
    "reason": "After 3 tries: Mean magnitude 0.351 <= 1.0"
  },
  "0572-7.mp4": {
    "keep": true,
    "gap_start": 38.62,
    "gap_end": 61.11,
    "reason": null
  },
  "0577-7.mp4": {
    "keep": false,
    "gap_start": null,
    "gap_end": null,
    "reason": "After 3 tries: Mean magnitude 0.706 <= 1.0"
  },
  "0579-7.mp4": {
    "keep": false,
    "gap_start": null,
    "gap_end": null,
    "reason": "After 3 tries: Mean magnitude 0.256 <= 1.0"
  },
  "0582-7.mp4": {
    "keep": false,
    "gap_start": null,
    "gap_end": null,
    "reason": "QUALITY_LOW"
  },
  "0592-7.mp4": {
    "keep": true,
    "gap_start": 19.31,
    "gap_end": 41.87,
    "reason": null
  },
  "0593-7.mp4": {
    "keep": false,
    "gap_start": null,
    "gap_end": null,
    "reason": "After 3 tries: Mean magnitude 0.849 <= 1.0"
  },
  "0596-7.mp4": {
    "keep": true,
    "gap_start": 17.91,
    "gap_end": 29.52,
    "reason": null
  },
  "0598-7.mp4": {
    "keep": false,
    "gap_start": null,
    "gap_end": null,
    "reason": "QUALITY_LOW"
  },
  "0601-7.mp4": {
    "keep": false,
    "gap_start": null,
    "gap_end": null,
    "reason": "After 3 tries: Mean magnitude 0.935 <= 1.0"
  },
  "0602-7.mp4": {
    "keep": false,
    "gap_start": null,
    "gap_end": null,
    "reason": "After 3 tries: Mean magnitude 0.492 <= 1.0"
  },
  "0604-7.mp4": {
    "keep": false,
    "gap_start": null,
    "gap_end": null,
    "reason": "QUALITY_LOW"
  },
  "0608-7.mp4": {
    "keep": false,
    "gap_start": null,
    "gap_end": null,
    "reason": "After 3 tries: Mean magnitude 0.599 <= 1.0"
  },
  "0613-7.mp4": {
    "keep": true,
    "gap_start": 12.86,
    "gap_end": 22.84,
    "reason": null
  },
  "0615-7.mp4": {
    "keep": false,
    "gap_start": null,
    "gap_end": null,
    "reason": "QUALITY_LOW"
  },
  "0617-7.mp4": {
    "keep": true,
    "gap_start": 4.38,
    "gap_end": 7.44,
    "reason": null
  },
  "0619-7.mp4": {
    "keep": false,
    "gap_start": null,
    "gap_end": null,
    "reason": "After 3 tries: Mean magnitude 0.991 <= 1.0"
  },
  "0622-7.mp4": {
    "keep": false,
    "gap_start": null,
    "gap_end": null,
    "reason": "QUALITY_LOW"
  },
  "0634-7.mp4": {
    "keep": true,
    "gap_start": 19.76,
    "gap_end": 32.47,
    "reason": null
  },
  "0642-7.mp4": {
    "keep": false,
    "gap_start": null,
    "gap_end": null,
    "reason": "After 3 tries: Mean magnitude 0.597 <= 1.0"
  },
  "0648-7.mp4": {
    "keep": false,
    "gap_start": null,
    "gap_end": null,
    "reason": "After 3 tries: Mean magnitude 0.940 <= 1.0"
  },
  "0649-7.mp4": {
    "keep": false,
    "gap_start": null,
    "gap_end": null,
    "reason": "After 3 tries: Mean magnitude 0.435 <= 1.0"
  },
  "0650-7.mp4": {
    "keep": true,
    "gap_start": 17.98,
    "gap_end": 33.42,
    "reason": null
  },
  "0653-7.mp4": {
    "keep": false,
    "gap_start": null,
    "gap_end": null,
    "reason": "QUALITY_LOW"
  },
  "0654-7.mp4": {
    "keep": true,
    "gap_start": 16.36,
    "gap_end": 32.46,
    "reason": null
  },
  "0659-7.mp4": {
    "keep": false,
    "gap_start": null,
    "gap_end": null,
    "reason": "QUALITY_LOW"
  },
  "0661-7.mp4": {
    "keep": false,
    "gap_start": null,
    "gap_end": null,
    "reason": "QUALITY_LOW"
  },
  "0662-7.mp4": {
    "keep": false,
    "gap_start": null,
    "gap_end": null,
    "reason": "QUALITY_LOW"
  },
  "0665-7.mp4": {
    "keep": false,
    "gap_start": null,
    "gap_end": null,
    "reason": "After 3 tries: Mean magnitude 0.403 <= 1.0"
  },
  "0666-7.mp4": {
    "keep": false,
    "gap_start": null,
    "gap_end": null,
    "reason": "QUALITY_LOW"
  },
  "0668-7.mp4": {
    "keep": false,
    "gap_start": null,
    "gap_end": null,
    "reason": "QUALITY_LOW"
  },
  "0669-7.mp4": {
    "keep": true,
    "gap_start": 13.05,
    "gap_end": 26.38,
    "reason": null
  },
  "0676-7.mp4": {
    "keep": false,
    "gap_start": null,
    "gap_end": null,
    "reason": "After 3 tries: Mean magnitude 0.463 <= 1.0"
  },
  "0681-7.mp4": {
    "keep": false,
    "gap_start": null,
    "gap_end": null,
    "reason": "After 3 tries: Mean magnitude 0.238 <= 1.0"
  },
  "0682-7.mp4": {
    "keep": false,
    "gap_start": null,
    "gap_end": null,
    "reason": "QUALITY_LOW"
  },
  "0683-7.mp4": {
    "keep": false,
    "gap_start": null,
    "gap_end": null,
    "reason": "After 3 tries: Mean magnitude 0.269 <= 1.0"
  },
  "0685-7.mp4": {
    "keep": true,
    "gap_start": 15.79,
    "gap_end": 25.59,
    "reason": null
  },
  "0686-7.mp4": {
    "keep": false,
    "gap_start": null,
    "gap_end": null,
    "reason": "After 3 tries: Mean magnitude 0.476 <= 1.0"
  },
  "0688-7.mp4": {
    "keep": false,
    "gap_start": null,
    "gap_end": null,
    "reason": "QUALITY_LOW"
  },
  "0691-7.mp4": {
    "keep": false,
    "gap_start": null,
    "gap_end": null,
    "reason": "After 3 tries: Mean magnitude 0.417 <= 1.0"
  },
  "0692-7.mp4": {
    "keep": false,
    "gap_start": null,
    "gap_end": null,
    "reason": "After 3 tries: Mean magnitude 0.469 <= 1.0"
  },
  "0693-7.mp4": {
    "keep": false,
    "gap_start": null,
    "gap_end": null,
    "reason": "QUALITY_LOW"
  },
  "0694-7.mp4": {
    "keep": false,
    "gap_start": null,
    "gap_end": null,
    "reason": "QUALITY_LOW"
  },
  "0696-7.mp4": {
    "keep": false,
    "gap_start": null,
    "gap_end": null,
    "reason": "QUALITY_LOW"
  },
  "0697-7.mp4": {
    "keep": false,
    "gap_start": null,
    "gap_end": null,
    "reason": "QUALITY_LOW"
  },
  "0698-7.mp4": {
    "keep": true,
    "gap_start": 7.53,
    "gap_end": 11.85,
    "reason": null
  },
  "0700-7.mp4": {
    "keep": false,
    "gap_start": null,
    "gap_end": null,
    "reason": "QUALITY_LOW"
  },
  "0703-7.mp4": {
    "keep": false,
    "gap_start": null,
    "gap_end": null,
    "reason": "QUALITY_LOW"
  },
  "0705-7.mp4": {
    "keep": false,
    "gap_start": null,
    "gap_end": null,
    "reason": "QUALITY_LOW"
  },
  "0714-7.mp4": {
    "keep": false,
    "gap_start": null,
    "gap_end": null,
    "reason": "After 3 tries: Mean magnitude 0.789 <= 1.0"
  },
  "0717-7.mp4": {
    "keep": false,
    "gap_start": null,
    "gap_end": null,
    "reason": "QUALITY_LOW"
  },
  "0718-7.mp4": {
    "keep": false,
    "gap_start": null,
    "gap_end": null,
    "reason": "After 3 tries: Mean magnitude 0.375 <= 1.0"
  },
  "0736-7.mp4": {
    "keep": false,
    "gap_start": null,
    "gap_end": null,
    "reason": "After 3 tries: Mean magnitude 0.202 <= 1.0"
  },
  "0739-7.mp4": {
    "keep": false,
    "gap_start": null,
    "gap_end": null,
    "reason": "QUALITY_LOW"
  },
  "0741-7.mp4": {
    "keep": false,
    "gap_start": null,
    "gap_end": null,
    "reason": "QUALITY_LOW"
  },
  "0744-7.mp4": {
    "keep": false,
    "gap_start": null,
    "gap_end": null,
    "reason": "QUALITY_LOW"
  },
  "0745-7.mp4": {
    "keep": false,
    "gap_start": null,
    "gap_end": null,
    "reason": "QUALITY_LOW"
  },
  "0746-7.mp4": {
    "keep": false,
    "gap_start": null,
    "gap_end": null,
    "reason": "QUALITY_LOW"
  },
  "0747-7.mp4": {
    "keep": false,
    "gap_start": null,
    "gap_end": null,
    "reason": "QUALITY_LOW"
  },
  "0748-7.mp4": {
    "keep": false,
    "gap_start": null,
    "gap_end": null,
    "reason": "QUALITY_LOW"
  },
  "0750-7.mp4": {
    "keep": false,
    "gap_start": null,
    "gap_end": null,
    "reason": "After 3 tries: Mean magnitude 0.807 <= 1.0"
  },
  "0753-7.mp4": {
    "keep": true,
    "gap_start": 7.82,
    "gap_end": 14.71,
    "reason": null
  },
  "0754-7.mp4": {
    "keep": true,
    "gap_start": 8.28,
    "gap_end": 18.63,
    "reason": null
  },
  "0768-7.mp4": {
    "keep": false,
    "gap_start": null,
    "gap_end": null,
    "reason": "QUALITY_LOW"
  },
  "0770-7.mp4": {
    "keep": true,
    "gap_start": 5.68,
    "gap_end": 12.76,
    "reason": null
  },
  "0774-7.mp4": {
    "keep": false,
    "gap_start": null,
    "gap_end": null,
    "reason": "After 3 tries: Mean magnitude 0.548 <= 1.0"
  },
  "0775-7.mp4": {
    "keep": false,
    "gap_start": null,
    "gap_end": null,
    "reason": "After 3 tries: Mean magnitude 0.788 <= 1.0"
  },
  "0785-7.mp4": {
    "keep": true,
    "gap_start": 5.18,
    "gap_end": 8.25,
    "reason": null
  },
  "0786-7.mp4": {
    "keep": false,
    "gap_start": null,
    "gap_end": null,
    "reason": "QUALITY_LOW"
  },
  "0788-7.mp4": {
    "keep": false,
    "gap_start": null,
    "gap_end": null,
    "reason": "After 3 tries: Mean magnitude 0.551 <= 1.0"
  },
  "0789-7.mp4": {
    "keep": true,
    "gap_start": 10.49,
    "gap_end": 16.12,
    "reason": null
  },
  "0791-7.mp4": {
    "keep": false,
    "gap_start": null,
    "gap_end": null,
    "reason": "After 3 tries: Mean magnitude 0.762 <= 1.0"
  },
  "0793-7.mp4": {
    "keep": true,
    "gap_start": 19.55,
    "gap_end": 33.96,
    "reason": null
  },
  "0795-7.mp4": {
    "keep": false,
    "gap_start": null,
    "gap_end": null,
    "reason": "QUALITY_LOW"
  },
  "0796-7.mp4": {
    "keep": true,
    "gap_start": 19.0,
    "gap_end": 40.39,
    "reason": null
  },
  "0798-7.mp4": {
    "keep": true,
    "gap_start": 7.41,
    "gap_end": 13.79,
    "reason": null
  },
  "0799-7.mp4": {
    "keep": false,
    "gap_start": null,
    "gap_end": null,
    "reason": "QUALITY_LOW"
  },
  "0807-7.mp4": {
    "keep": false,
    "gap_start": null,
    "gap_end": null,
    "reason": "After 3 tries: Mean magnitude 0.239 <= 1.0"
  },
  "0809-7.mp4": {
    "keep": true,
    "gap_start": 20.83,
    "gap_end": 38.81,
    "reason": null
  },
  "0813-7.mp4": {
    "keep": false,
    "gap_start": null,
    "gap_end": null,
    "reason": "After 3 tries: Mean magnitude 0.950 <= 1.0"
  },
  "0820-7.mp4": {
    "keep": false,
    "gap_start": null,
    "gap_end": null,
    "reason": "QUALITY_LOW"
  },
  "0829-7.mp4": {
    "keep": false,
    "gap_start": null,
    "gap_end": null,
    "reason": "QUALITY_LOW"
  },
  "0831-7.mp4": {
    "keep": false,
    "gap_start": null,
    "gap_end": null,
    "reason": "QUALITY_LOW"
  },
  "0832-7.mp4": {
    "keep": false,
    "gap_start": null,
    "gap_end": null,
    "reason": "After 3 tries: Mean magnitude 0.430 <= 1.0"
  },
  "0839-7.mp4": {
    "keep": false,
    "gap_start": null,
    "gap_end": null,
    "reason": "After 3 tries: Mean magnitude 0.615 <= 1.0"
  },
  "0840-7.mp4": {
    "keep": false,
    "gap_start": null,
    "gap_end": null,
    "reason": "QUALITY_LOW"
  },
  "0842-7.mp4": {
    "keep": false,
    "gap_start": null,
    "gap_end": null,
    "reason": "After 3 tries: Mean magnitude 0.067 <= 1.0"
  },
  "0853-7.mp4": {
    "keep": false,
    "gap_start": null,
    "gap_end": null,
    "reason": "QUALITY_LOW"
  },
  "0855-7.mp4": {
    "keep": false,
    "gap_start": null,
    "gap_end": null,
    "reason": "After 3 tries: Mean magnitude 0.125 <= 1.0"
  },
  "0856-7.mp4": {
    "keep": true,
    "gap_start": 17.8,
    "gap_end": 39.67,
    "reason": null
  },
  "0863-7.mp4": {
    "keep": false,
    "gap_start": null,
    "gap_end": null,
    "reason": "QUALITY_LOW"
  },
  "0873-7.mp4": {
    "keep": false,
    "gap_start": null,
    "gap_end": null,
    "reason": "QUALITY_LOW"
  },
  "0876-7.mp4": {
    "keep": true,
    "gap_start": 8.43,
    "gap_end": 12.23,
    "reason": null
  },
  "0878-7.mp4": {
    "keep": true,
    "gap_start": 8.9,
    "gap_end": 15.42,
    "reason": null
  },
  "0882-7.mp4": {
    "keep": false,
    "gap_start": null,
    "gap_end": null,
    "reason": "After 3 tries: Mean magnitude 0.887 <= 1.0"
  },
  "0883-7.mp4": {
    "keep": true,
    "gap_start": 5.09,
    "gap_end": 12.04,
    "reason": null
  },
  "0888-7.mp4": {
    "keep": false,
    "gap_start": null,
    "gap_end": null,
    "reason": "After 3 tries: Mean magnitude 0.532 <= 1.0"
  },
  "0890-7.mp4": {
    "keep": true,
    "gap_start": 4.75,
    "gap_end": 10.13,
    "reason": null
  },
  "0891-7.mp4": {
    "keep": false,
    "gap_start": null,
    "gap_end": null,
    "reason": "QUALITY_LOW"
  },
  "0902-7.mp4": {
    "keep": false,
    "gap_start": null,
    "gap_end": null,
    "reason": "After 3 tries: Mean magnitude 0.374 <= 1.0"
  },
  "0906-7.mp4": {
    "keep": false,
    "gap_start": null,
    "gap_end": null,
    "reason": "After 3 tries: Mean magnitude 0.363 <= 1.0"
  },
  "0917-7.mp4": {
    "keep": false,
    "gap_start": null,
    "gap_end": null,
    "reason": "After 3 tries: Mean magnitude 0.573 <= 1.0"
  },
  "0922-7.mp4": {
    "keep": false,
    "gap_start": null,
    "gap_end": null,
    "reason": "After 3 tries: Mean magnitude 0.570 <= 1.0"
  },
  "0925-7.mp4": {
    "keep": false,
    "gap_start": null,
    "gap_end": null,
    "reason": "QUALITY_LOW"
  },
  "0928-7.mp4": {
    "keep": false,
    "gap_start": null,
    "gap_end": null,
    "reason": "QUALITY_LOW"
  },
  "0930-7.mp4": {
    "keep": false,
    "gap_start": null,
    "gap_end": null,
    "reason": "QUALITY_LOW"
  },
  "0934-7.mp4": {
    "keep": false,
    "gap_start": null,
    "gap_end": null,
    "reason": "QUALITY_LOW"
  },
  "0935-7.mp4": {
    "keep": false,
    "gap_start": null,
    "gap_end": null,
    "reason": "After 3 tries: Mean magnitude 0.342 <= 1.0"
  },
  "0936-7.mp4": {
    "keep": false,
    "gap_start": null,
    "gap_end": null,
    "reason": "After 3 tries: Mean magnitude 0.494 <= 1.0"
  },
  "0937-7.mp4": {
    "keep": false,
    "gap_start": null,
    "gap_end": null,
    "reason": "After 3 tries: Mean magnitude 0.728 <= 1.0"
  },
  "0938-7.mp4": {
    "keep": false,
    "gap_start": null,
    "gap_end": null,
    "reason": "QUALITY_LOW"
  },
  "0944-7.mp4": {
    "keep": false,
    "gap_start": null,
    "gap_end": null,
    "reason": "After 3 tries: Mean magnitude 0.527 <= 1.0"
  },
  "0945-7.mp4": {
    "keep": true,
    "gap_start": 6.17,
    "gap_end": 13.33,
    "reason": null
  },
  "0948-7.mp4": {
    "keep": false,
    "gap_start": null,
    "gap_end": null,
    "reason": "QUALITY_LOW"
  },
  "0951-7.mp4": {
    "keep": true,
    "gap_start": 5.36,
    "gap_end": 9.0,
    "reason": null
  },
  "0953-7.mp4": {
    "keep": true,
    "gap_start": 8.11,
    "gap_end": 11.85,
    "reason": null
  },
  "0958-7.mp4": {
    "keep": false,
    "gap_start": null,
    "gap_end": null,
    "reason": "After 3 tries: Mean magnitude 0.529 <= 1.0"
  },
  "0963-7.mp4": {
    "keep": true,
    "gap_start": 21.3,
    "gap_end": 36.6,
    "reason": null
  },
  "0966-7.mp4": {
    "keep": false,
    "gap_start": null,
    "gap_end": null,
    "reason": "QUALITY_LOW"
  },
  "0969-7.mp4": {
    "keep": false,
    "gap_start": null,
    "gap_end": null,
    "reason": "QUALITY_LOW"
  },
  "0977-7.mp4": {
    "keep": false,
    "gap_start": null,
    "gap_end": null,
    "reason": "QUALITY_LOW"
  },
  "0981-7.mp4": {
    "keep": true,
    "gap_start": 12.98,
    "gap_end": 21.39,
    "reason": null
  },
  "0982-7.mp4": {
    "keep": true,
    "gap_start": 12.84,
    "gap_end": 17.52,
    "reason": null
  },
  "0987-7.mp4": {
    "keep": false,
    "gap_start": null,
    "gap_end": null,
    "reason": "After 3 tries: Mean magnitude 0.545 <= 1.0"
  },
  "0988-7.mp4": {
    "keep": false,
    "gap_start": null,
    "gap_end": null,
    "reason": "QUALITY_LOW"
  },
  "0989-7.mp4": {
    "keep": false,
    "gap_start": null,
    "gap_end": null,
    "reason": "QUALITY_LOW"
  },
  "0990-7.mp4": {
    "keep": false,
    "gap_start": null,
    "gap_end": null,
    "reason": "After 3 tries: Mean magnitude 0.506 <= 1.0"
  },
  "0992-7.mp4": {
    "keep": false,
    "gap_start": null,
    "gap_end": null,
    "reason": "After 3 tries: Mean magnitude 0.737 <= 1.0"
  },
  "0997-7.mp4": {
    "keep": false,
    "gap_start": null,
    "gap_end": null,
    "reason": "QUALITY_LOW"
  },
  "0998-7.mp4": {
    "keep": true,
    "gap_start": 14.9,
    "gap_end": 30.03,
    "reason": null
  },
  "1000-7.mp4": {
    "keep": true,
    "gap_start": 5.71,
    "gap_end": 12.65,
    "reason": null
  },
  "1006-7.mp4": {
    "keep": true,
    "gap_start": 15.82,
    "gap_end": 30.25,
    "reason": null
  },
  "1013-7.mp4": {
    "keep": false,
    "gap_start": null,
    "gap_end": null,
    "reason": "After 3 tries: Mean magnitude 0.250 <= 1.0"
  },
  "1017-7.mp4": {
    "keep": false,
    "gap_start": null,
    "gap_end": null,
    "reason": "After 3 tries: Mean magnitude 0.919 <= 1.0"
  },
  "1021-7.mp4": {
    "keep": true,
    "gap_start": 14.95,
    "gap_end": 26.18,
    "reason": null
  },
  "1024-7.mp4": {
    "keep": false,
    "gap_start": null,
    "gap_end": null,
    "reason": "After 3 tries: Mean magnitude 0.655 <= 1.0"
  },
  "1032-7.mp4": {
    "keep": false,
    "gap_start": null,
    "gap_end": null,
    "reason": "QUALITY_LOW"
  },
  "1033-7.mp4": {
    "keep": false,
    "gap_start": null,
    "gap_end": null,
    "reason": "After 3 tries: Mean magnitude 0.640 <= 1.0"
  },
  "1042-7.mp4": {
    "keep": false,
    "gap_start": null,
    "gap_end": null,
    "reason": "After 3 tries: Mean magnitude 0.406 <= 1.0"
  },
  "1043-7.mp4": {
    "keep": false,
    "gap_start": null,
    "gap_end": null,
    "reason": "After 3 tries: Mean magnitude 0.145 <= 1.0"
  },
  "1048-7.mp4": {
    "keep": false,
    "gap_start": null,
    "gap_end": null,
    "reason": "After 3 tries: Mean magnitude 0.627 <= 1.0"
  },
  "1052-7.mp4": {
    "keep": false,
    "gap_start": null,
    "gap_end": null,
    "reason": "QUALITY_LOW"
  },
  "1056-7.mp4": {
    "keep": false,
    "gap_start": null,
    "gap_end": null,
    "reason": "QUALITY_LOW"
  },
  "1057-7.mp4": {
    "keep": false,
    "gap_start": null,
    "gap_end": null,
    "reason": "After 3 tries: Mean magnitude 0.258 <= 1.0"
  },
  "1058-7.mp4": {
    "keep": true,
    "gap_start": 21.43,
    "gap_end": 41.17,
    "reason": null
  },
  "1061-7.mp4": {
    "keep": false,
    "gap_start": null,
    "gap_end": null,
    "reason": "After 3 tries: Mean magnitude 0.212 <= 1.0"
  },
  "1062-7.mp4": {
    "keep": false,
    "gap_start": null,
    "gap_end": null,
    "reason": "After 3 tries: Mean magnitude 0.397 <= 1.0"
  },
  "1065-7.mp4": {
    "keep": true,
    "gap_start": 12.56,
    "gap_end": 23.5,
    "reason": null
  },
  "1066-7.mp4": {
    "keep": false,
    "gap_start": null,
    "gap_end": null,
    "reason": "After 3 tries: Mean magnitude 0.219 <= 1.0"
  },
  "1068-7.mp4": {
    "keep": true,
    "gap_start": 4.84,
    "gap_end": 10.35,
    "reason": null
  },
  "1072-7.mp4": {
    "keep": false,
    "gap_start": null,
    "gap_end": null,
    "reason": "QUALITY_LOW"
  },
  "1103-7.mp4": {
    "keep": true,
    "gap_start": 19.7,
    "gap_end": 37.66,
    "reason": null
  },
  "1104-7.mp4": {
    "keep": false,
    "gap_start": null,
    "gap_end": null,
    "reason": "After 3 tries: Mean magnitude 0.143 <= 1.0"
  },
  "1107-7.mp4": {
    "keep": false,
    "gap_start": null,
    "gap_end": null,
    "reason": "After 3 tries: Mean magnitude 0.284 <= 1.0"
  },
  "1108-7.mp4": {
    "keep": false,
    "gap_start": null,
    "gap_end": null,
    "reason": "After 3 tries: Mean magnitude 0.374 <= 1.0"
  },
  "1109-7.mp4": {
    "keep": false,
    "gap_start": null,
    "gap_end": null,
    "reason": "After 3 tries: Mean magnitude 0.192 <= 1.0"
  },
  "1110-7.mp4": {
    "keep": false,
    "gap_start": null,
    "gap_end": null,
    "reason": "After 3 tries: Mean magnitude 0.172 <= 1.0"
  },
  "1118-7.mp4": {
    "keep": true,
    "gap_start": 9.86,
    "gap_end": 16.86,
    "reason": null
  },
  "1123-7.mp4": {
    "keep": false,
    "gap_start": null,
    "gap_end": null,
    "reason": "QUALITY_LOW"
  },
  "1126-7.mp4": {
    "keep": true,
    "gap_start": 4.35,
    "gap_end": 10.3,
    "reason": null
  },
  "1128-7.mp4": {
    "keep": true,
    "gap_start": 15.93,
    "gap_end": 29.23,
    "reason": null
  },
  "1131-7.mp4": {
    "keep": false,
    "gap_start": null,
    "gap_end": null,
    "reason": "QUALITY_LOW"
  },
  "1132-7.mp4": {
    "keep": false,
    "gap_start": null,
    "gap_end": null,
    "reason": "QUALITY_LOW"
  },
  "1133-7.mp4": {
    "keep": false,
    "gap_start": null,
    "gap_end": null,
    "reason": "After 3 tries: Mean magnitude 0.338 <= 1.0"
  },
  "1136-7.mp4": {
    "keep": false,
    "gap_start": null,
    "gap_end": null,
    "reason": "After 3 tries: Mean magnitude 0.203 <= 1.0"
  },
  "1141-7.mp4": {
    "keep": true,
    "gap_start": 3.7,
    "gap_end": 7.89,
    "reason": null
  },
  "1150-7.mp4": {
    "keep": false,
    "gap_start": null,
    "gap_end": null,
    "reason": "After 3 tries: Mean magnitude 0.052 <= 1.0"
  },
  "1151-7.mp4": {
    "keep": false,
    "gap_start": null,
    "gap_end": null,
    "reason": "After 3 tries: Mean magnitude 0.323 <= 1.0"
  },
  "1171-7.mp4": {
    "keep": false,
    "gap_start": null,
    "gap_end": null,
    "reason": "After 3 tries: Mean magnitude 0.507 <= 1.0"
  },
  "1174-7.mp4": {
    "keep": true,
    "gap_start": 4.33,
    "gap_end": 7.77,
    "reason": null
  },
  "1179-7.mp4": {
    "keep": true,
    "gap_start": 6.28,
    "gap_end": 12.45,
    "reason": null
  },
  "1184-7.mp4": {
    "keep": true,
    "gap_start": 3.47,
    "gap_end": 8.97,
    "reason": null
  },
  "1188-7.mp4": {
    "keep": true,
    "gap_start": 4.91,
    "gap_end": 8.13,
    "reason": null
  },
  "1191-7.mp4": {
    "keep": true,
    "gap_start": 4.16,
    "gap_end": 8.47,
    "reason": null
  },
  "1193-7.mp4": {
    "keep": true,
    "gap_start": 9.98,
    "gap_end": 15.93,
    "reason": null
  },
  "1194-7.mp4": {
    "keep": true,
    "gap_start": 5.72,
    "gap_end": 8.86,
    "reason": null
  },
  "1196-7.mp4": {
    "keep": false,
    "gap_start": null,
    "gap_end": null,
    "reason": "After 3 tries: Mean magnitude 0.945 <= 1.0"
  },
  "1197-7.mp4": {
    "keep": false,
    "gap_start": null,
    "gap_end": null,
    "reason": "QUALITY_LOW"
  },
  "1198-7.mp4": {
    "keep": false,
    "gap_start": null,
    "gap_end": null,
    "reason": "After 3 tries: Mean magnitude 0.591 <= 1.0"
  },
  "1201-7.mp4": {
    "keep": true,
    "gap_start": 27.45,
    "gap_end": 44.24,
    "reason": null
  },
  "1202-7.mp4": {
    "keep": false,
    "gap_start": null,
    "gap_end": null,
    "reason": "After 3 tries: Mean magnitude 0.271 <= 1.0"
  },
  "1204-7.mp4": {
    "keep": true,
    "gap_start": 16.63,
    "gap_end": 29.05,
    "reason": null
  },
  "1205-7.mp4": {
    "keep": false,
    "gap_start": null,
    "gap_end": null,
    "reason": "QUALITY_LOW"
  },
  "1208-7.mp4": {
    "keep": true,
    "gap_start": 6.56,
    "gap_end": 15.98,
    "reason": null
  },
  "1218-7.mp4": {
    "keep": false,
    "gap_start": null,
    "gap_end": null,
    "reason": "QUALITY_LOW"
  },
  "1220-7.mp4": {
    "keep": false,
    "gap_start": null,
    "gap_end": null,
    "reason": "After 3 tries: Mean magnitude 0.788 <= 1.0"
  },
  "1221-7.mp4": {
    "keep": true,
    "gap_start": 4.63,
    "gap_end": 8.78,
    "reason": null
  },
  "1226-7.mp4": {
    "keep": false,
    "gap_start": null,
    "gap_end": null,
    "reason": "After 3 tries: Mean magnitude 0.445 <= 1.0"
  },
  "1227-7.mp4": {
    "keep": false,
    "gap_start": null,
    "gap_end": null,
    "reason": "QUALITY_LOW"
  },
  "1232-7.mp4": {
    "keep": true,
    "gap_start": 4.32,
    "gap_end": 10.02,
    "reason": null
  },
  "1241-7.mp4": {
    "keep": false,
    "gap_start": null,
    "gap_end": null,
    "reason": "After 3 tries: Mean magnitude 0.313 <= 1.0"
  },
  "1243-7.mp4": {
    "keep": true,
    "gap_start": 18.7,
    "gap_end": 29.31,
    "reason": null
  },
  "1244-7.mp4": {
    "keep": false,
    "gap_start": null,
    "gap_end": null,
    "reason": "QUALITY_LOW"
  },
  "1245-7.mp4": {
    "keep": false,
    "gap_start": null,
    "gap_end": null,
    "reason": "After 3 tries: Mean magnitude 0.942 <= 1.0"
  },
  "1250-7.mp4": {
    "keep": true,
    "gap_start": 7.28,
    "gap_end": 13.37,
    "reason": null
  },
  "1252-7.mp4": {
    "keep": false,
    "gap_start": null,
    "gap_end": null,
    "reason": "After 3 tries: Mean magnitude 0.225 <= 1.0"
  },
  "1256-7.mp4": {
    "keep": false,
    "gap_start": null,
    "gap_end": null,
    "reason": "QUALITY_LOW"
  },
  "1257-7.mp4": {
    "keep": true,
    "gap_start": 6.65,
    "gap_end": 9.8,
    "reason": null
  },
  "1258-7.mp4": {
    "keep": false,
    "gap_start": null,
    "gap_end": null,
    "reason": "QUALITY_LOW"
  },
  "1263-7.mp4": {
    "keep": false,
    "gap_start": null,
    "gap_end": null,
    "reason": "QUALITY_LOW"
  },
  "1264-7.mp4": {
    "keep": false,
    "gap_start": null,
    "gap_end": null,
    "reason": "QUALITY_LOW"
  },
  "1267-7.mp4": {
    "keep": false,
    "gap_start": null,
    "gap_end": null,
    "reason": "QUALITY_LOW"
  },
  "1280-7.mp4": {
    "keep": true,
    "gap_start": 9.11,
    "gap_end": 15.5,
    "reason": null
  },
  "1282-7.mp4": {
    "keep": true,
    "gap_start": 24.96,
    "gap_end": 53.37,
    "reason": null
  },
  "1284-7.mp4": {
    "keep": true,
    "gap_start": 4.57,
    "gap_end": 9.8,
    "reason": null
  },
  "1285-7.mp4": {
    "keep": true,
    "gap_start": 7.95,
    "gap_end": 11.42,
    "reason": null
  },
  "1286-7.mp4": {
    "keep": false,
    "gap_start": null,
    "gap_end": null,
    "reason": "After 3 tries: Mean magnitude 0.360 <= 1.0"
  },
  "1287-7.mp4": {
    "keep": false,
    "gap_start": null,
    "gap_end": null,
    "reason": "After 3 tries: Mean magnitude 0.407 <= 1.0"
  },
  "1300-7.mp4": {
    "keep": true,
    "gap_start": 16.84,
    "gap_end": 34.42,
    "reason": null
  },
  "1301-7.mp4": {
    "keep": false,
    "gap_start": null,
    "gap_end": null,
    "reason": "After 3 tries: Mean magnitude 0.556 <= 1.0"
  },
  "1304-7.mp4": {
    "keep": false,
    "gap_start": null,
    "gap_end": null,
    "reason": "QUALITY_LOW"
  },
  "1306-7.mp4": {
    "keep": false,
    "gap_start": null,
    "gap_end": null,
    "reason": "After 3 tries: Mean magnitude 0.508 <= 1.0"
  },
  "1309-7.mp4": {
    "keep": false,
    "gap_start": null,
    "gap_end": null,
    "reason": "QUALITY_LOW"
  },
  "1311-7.mp4": {
    "keep": false,
    "gap_start": null,
    "gap_end": null,
    "reason": "QUALITY_LOW"
  },
  "1313-7.mp4": {
    "keep": true,
    "gap_start": 15.25,
    "gap_end": 33.01,
    "reason": null
  },
  "1314-7.mp4": {
    "keep": true,
    "gap_start": 14.1,
    "gap_end": 23.71,
    "reason": null
  },
  "1315-7.mp4": {
    "keep": true,
    "gap_start": 24.41,
    "gap_end": 40.87,
    "reason": null
  },
  "1320-7.mp4": {
    "keep": false,
    "gap_start": null,
    "gap_end": null,
    "reason": "QUALITY_LOW"
  },
  "1326-7.mp4": {
    "keep": false,
    "gap_start": null,
    "gap_end": null,
    "reason": "QUALITY_LOW"
  },
  "1331-7.mp4": {
    "keep": false,
    "gap_start": null,
    "gap_end": null,
    "reason": "QUALITY_LOW"
  },
  "1335-7.mp4": {
    "keep": false,
    "gap_start": null,
    "gap_end": null,
    "reason": "After 3 tries: Mean magnitude 0.593 <= 1.0"
  },
  "1336-7.mp4": {
    "keep": false,
    "gap_start": null,
    "gap_end": null,
    "reason": "After 3 tries: Mean magnitude 0.775 <= 1.0"
  },
  "1339-7.mp4": {
    "keep": false,
    "gap_start": null,
    "gap_end": null,
    "reason": "QUALITY_LOW"
  },
  "1343-7.mp4": {
    "keep": true,
    "gap_start": 20.47,
    "gap_end": 35.64,
    "reason": null
  }
}